ngr/__init__.py
ngr-0.0.1.dist-info/METADATA
ngr-0.0.1.dist-info/WHEEL
ngr-0.0.1.dist-info/top_level.txt
ngr-0.0.1.dist-info/RECORD
