Metadata-Version: 2.4
Name: ngr
Version: 0.0.1
Summary: Python interface for NGR (Next Generation Reporting)
Author-email: Alejandro Verri Kozlowski <averri@fi.uba.ar>
License: MIT
Project-URL: Homepage, https://github.com/averriK/NGR
Project-URL: Source, https://github.com/averriK/NGR
Keywords: reporting,ngr,tables,plots
Classifier: Programming Language :: Python :: 3
Classifier: License :: OSI Approved :: MIT License
Classifier: Operating System :: OS Independent
Requires-Python: >=3.9
